{
  "canisters": {
    "binary_option_market": {
      "main": "canisters/binary_option_market/src/main.mo",
      "type": "motoko",
      "dependencies": [
        "icp_ledger_canister"
      ]
    },
    "icp_ledger_canister": {
      "type": "custom",
      "candid": "https://raw.githubusercontent.com/dfinity/ic/aba60ffbc46acfc8990bf4d5685c1360bd7026b9/rs/ledger_suite/icp/ledger.did",
      "wasm": "https://download.dfinity.systems/ic/aba60ffbc46acfc8990bf4d5685c1360bd7026b9/canisters/ledger-canister.wasm.gz",
      "remote": {
        "id": {
          "ic": "ryjl3-tyaaa-aaaaa-aaaba-cai"
        }
      }
    },
    "internet_identity": {
      "type": "pull",
      "id": "rdmx6-jaaaa-aaaaa-aaadq-cai"
    },
    "invoice_canister": {
      "main": "canisters/invoice/src/main.mo",
      "type": "motoko",
      "dependencies": [
        "icp_ledger_canister"
      ]
    },
    "chain_fusion": {
      "candid": "canisters/chain_fusion/chain_fusion.did",
      "package": "chain_fusion",
      "type": "rust",
      "dependencies": [
        "evm_rpc"
      ],
      "specified_id": "2222s-4iaaa-aaaaf-ax2uq-cai",
      "metadata": [
        {
          "name": "candid:service"
        }
      ]
    },
    "evm_rpc": {
      "type": "custom",
      "candid": "https://github.com/internet-computer-protocol/evm-rpc-canister/releases/latest/download/evm_rpc.did",
      "wasm": "https://github.com/internet-computer-protocol/evm-rpc-canister/releases/latest/download/evm_rpc.wasm.gz",
      "remote": {
        "id": {
          "ic": "7hfb6-caaaa-aaaar-qadga-cai"
        }
      },
      "specified_id": "7hfb6-caaaa-aaaar-qadga-cai",
      "init_arg": "(record { nodesInSubnet = 28 })"
    },
    "xrc": {
      "type": "custom",
      "candid": "https://raw.githubusercontent.com/dfinity/exchange-rate-canister/51428a562622c5fb3f0bf24214cff77f27ce9bdf/src/xrc/xrc.did",
      "wasm": "https://github.com/dfinity/exchange-rate-canister/releases/download/2024.04.05/xrc.wasm.gz",
      "remote": {
        "id": {
          "ic": "uf6dk-hyaaa-aaaaq-qaaaq-cai"
        }
      },
      "specified_id": "uf6dk-hyaaa-aaaaq-qaaaq-cai"
    }
  },
  "defaults": {
    "build": {
      "args": "",
      "packtool": "mops sources"
    }
  },
  "output_env_file": ".env",
  "version": 1
}